archguide_mcp_python/__init__.py
archguide_mcp_python/server.py
archguide_mcp_python/config/__init__.py
archguide_mcp_python/config/models.py
archguide_mcp_python/guidelines/architecture/domain-driven-design.md
archguide_mcp_python/guidelines/cloud-native/api-design.md
archguide_mcp_python/guidelines/microservices/data-management.md
archguide_mcp_python/guidelines/security/authentication.md
archguide_mcp_python/guidelines/serverless/.category.json
archguide_mcp_python/models/__init__.py
archguide_mcp_python/models/types.py
archguide_mcp_python/parsers/__init__.py
archguide_mcp_python/parsers/content.py
archguide_mcp_python/sources/__init__.py
archguide_mcp_python/sources/base.py
archguide_mcp_python/sources/git.py
archguide_mcp_python/sources/local.py
archguide_mcp_python/sources/registry.py
archguide_mcp_python/storage/__init__.py
archguide_mcp_python/storage/filesystem.py
archguide_mcp_python/storage/multisource.py
archguide_mcp_python/storage/search.py
archguide_mcp_python/storage/store.py
archguide_mcp_python/utils/__init__.py
archguide_mcp_python/utils/cache.py
archguide_mcp_python/utils/formatters.py
archguide_mcp_python-0.4.0.dist-info/METADATA
archguide_mcp_python-0.4.0.dist-info/WHEEL
archguide_mcp_python-0.4.0.dist-info/entry_points.txt
archguide_mcp_python-0.4.0.dist-info/licenses/LICENSE
archguide_mcp_python-0.4.0.dist-info/RECORD
