Metadata-Version: 2.4
Name: archguide-mcp-python
Version: 0.4.0
Summary: Architecture Guidelines MCP Server - Inject architectural best practices into AI workflows
Project-URL: Homepage, https://github.com/ioansalau/archguide-mcp-python
Project-URL: Bug Reports, https://github.com/ioansalau/archguide-mcp-python/issues
Project-URL: Source, https://github.com/ioansalau/archguide-mcp-python
Project-URL: Documentation, https://github.com/ioansalau/archguide-mcp-python#readme
Author-email: Ioan Salau <salauioan@yahoo.com>
Maintainer-email: Ioan Salau <salauioan@yahoo.com>
License: MIT
License-File: LICENSE
Keywords: ai,architecture,best-practices,claude,design-patterns,fastmcp,guidelines,mcp,microservices,patterns,software-architecture
Classifier: Development Status :: 4 - Beta
Classifier: Intended Audience :: Developers
Classifier: Operating System :: OS Independent
Classifier: Programming Language :: Python :: 3
Classifier: Programming Language :: Python :: 3.12
Classifier: Topic :: Software Development :: Documentation
Classifier: Topic :: Software Development :: Libraries :: Python Modules
Classifier: Topic :: System :: Systems Administration
Classifier: Typing :: Typed
Requires-Python: >=3.12
Requires-Dist: click>=8.0.0
Requires-Dist: fastmcp>=0.9.0
Requires-Dist: pydantic-settings>=2.0.0
Requires-Dist: pydantic>=2.0.0
Requires-Dist: python-frontmatter>=1.0.0
Requires-Dist: pyyaml>=6.0.0
Requires-Dist: whoosh>=2.7.0
Provides-Extra: dev
Requires-Dist: black>=23.0.0; extra == 'dev'
Requires-Dist: mypy>=1.0.0; extra == 'dev'
Requires-Dist: pytest-asyncio>=0.21.0; extra == 'dev'
Requires-Dist: pytest>=7.0.0; extra == 'dev'
Requires-Dist: ruff>=0.1.0; extra == 'dev'
